{
  "week_info": {
    "ood": " 7 нечётная ",
    "start_with": " с 12 октября 2020 "
  },
  "1": {
    "date": " пн, 12 окт.",
    "day": "mondey",
    "subjects_list": [
      {
        "num": 1,
        "time": "08:50 - 10:25",
        "subject": "Нет занятий"
      },
      {
        "num": 2,
        "time": "10:40 - 12:15",
        "subject": "Нет занятий"
      },
      {
        "num": 3,
        "time": "13:00 - 14:35",
        "subject": "Нет занятий"
      },
      {
        "num": 4,
        "time": "14:50 - 16:25",
        "subject": {
          "full_name": "Системный анализ",
          "kind": "Практика",
          "auditoriums": "ф 437",
          "group": "Кориков А.М."
        }
      },
      {
        "num": 5,
        "time": "17:10 - 18:45",
        "subject": {
          "full_name": "ТЯПиМТ",
          "kind": "Лабораторная работа",
          "auditoriums": "ф 435",
          "group": "Романенко В.В."
        }
      },
      {
        "num": 6,
        "time": "19:00 - 20:35",
        "subject": {
          "full_name": "ТЯПиМТ",
          "kind": "Лабораторная работа",
          "auditoriums": "ф 435",
          "group": "Романенко В.В."
        }
      }
    ]
  },
  "2": {
    "date": " вт, 13 окт.",
    "day": "tuesday",
    "subjects_list": [
      {
        "num": 1,
        "time": "08:50 - 10:25",
        "subject": {
          "full_name": "ФиЛП",
          "kind": "Лекция",
          "auditoriums": "",
          "group": "Алферов С.М.",
          "note": "Реализуется в ЭИОС"
        }
      },
      {
        "num": 2,
        "time": "10:40 - 12:15",
        "subject": {
          "full_name": "ПиТСКС",
          "kind": "Лекция",
          "auditoriums": "",
          "group": "Абанеев Э.Р.",
          "note": "Реализуется в ЭИОС"
        }
      },
      {
        "num": 3,
        "time": "13:00 - 14:35",
        "subject": {
          "full_name": "ТЯПиМТ",
          "kind": "Лекция",
          "auditoriums": "",
          "group": "Романенко В.В.",
          "note": "Реализуется в ЭИОС"
        }
      },
      {
        "num": 4,
        "time": "14:50 - 16:25",
        "subject": "Нет занятий"
      },
      {
        "num": 5,
        "time": "17:10 - 18:45",
        "subject": "Нет занятий"
      },
      {
        "num": 6,
        "time": "19:00 - 20:35",
        "subject": "Нет занятий"
      }
    ]
  },
  "3": {
    "date": " ср, 14 окт.",
    "day": "wednesday",
    "subjects_list": [
      {
        "num": 1,
        "time": "08:50 - 10:25",
        "subject": "Нет занятий"
      },
      {
        "num": 2,
        "time": "10:40 - 12:15",
        "subject": "Нет занятий"
      },
      {
        "num": 3,
        "time": "13:00 - 14:35",
        "subject": "Нет занятий"
      },
      {
        "num": 4,
        "time": "14:50 - 16:25",
        "subject": {
          "full_name": "Правоведение",
          "kind": "Практика",
          "auditoriums": "ф 128",
          "group": "Петрова С.А."
        }
      },
      {
        "num": 5,
        "time": "17:10 - 18:45",
        "subject": {
          "full_name": "ТЯПиМТ",
          "kind": "Практика",
          "auditoriums": "ф 401",
          "group": "Романенко В.В."
        }
      },
      {
        "num": 6,
        "time": "19:00 - 20:35",
        "subject": {
          "full_name": "Системный анализ",
          "kind": "Лабораторная работа",
          "auditoriums": "ф 437",
          "group": "Кориков А.М."
        }
      }
    ]
  },
  "4": {
    "date": " чт, 15 окт.",
    "day": "thursday",
    "subjects_list": [
      {
        "num": 1,
        "time": "08:50 - 10:25",
        "subject": {
          "full_name": "ПОДМИГПО",
          "kind": "Лекция",
          "auditoriums": "ф 435",
          "group": "Катаев М.Ю."
        }
      },
      {
        "num": 2,
        "time": "10:40 - 12:15",
        "subject": {
          "full_name": "ПОДМИГПО",
          "kind": "Практика",
          "auditoriums": "ф 435",
          "group": "Катаев М.Ю."
        }
      },
      {
        "num": 3,
        "time": "13:00 - 14:35",
        "subject": {
          "full_name": "ПОДМИГПО",
          "kind": "Лабораторная работа",
          "auditoriums": "ф 435",
          "group": "Лукьянов А.К."
        }
      },
      {
        "num": 4,
        "time": "14:50 - 16:25",
        "subject": "Нет занятий"
      },
      {
        "num": 5,
        "time": "17:10 - 18:45",
        "subject": "Нет занятий"
      },
      {
        "num": 6,
        "time": "19:00 - 20:35",
        "subject": "Нет занятий"
      }
    ]
  },
  "5": {
    "date": " пт, 16 окт.",
    "day": "friday",
    "subjects_list": [
      {
        "num": 1,
        "time": "08:50 - 10:25",
        "subject": "Нет занятий"
      },
      {
        "num": 2,
        "time": "10:40 - 12:15",
        "subject": "Нет занятий"
      },
      {
        "num": 3,
        "time": "13:00 - 14:35",
        "subject": "Нет занятий"
      },
      {
        "num": 4,
        "time": "14:50 - 16:25",
        "subject": "Нет занятий"
      },
      {
        "num": 5,
        "time": "17:10 - 18:45",
        "subject": {
          "full_name": "Системный анализ",
          "kind": "Практика",
          "auditoriums": "ф 401",
          "group": "Кориков А.М."
        }
      },
      {
        "num": 6,
        "time": "19:00 - 20:35",
        "subject": {
          "full_name": "ФиЛП",
          "kind": "Практика",
          "auditoriums": "ф 401",
          "group": "Алферов С.М."
        }
      }
    ]
  },
  "6": {
    "date": " сб, 17 окт.",
    "day": "saturday",
    "subjects_list": [
      {
        "num": 1,
        "time": "08:50 - 10:25",
        "subject": {
          "full_name": "Системы цифровой обработки сигналов",
          "kind": "Лекция",
          "auditoriums": "",
          "group": "Воронин Б.А.",
          "note": "Реализуется в ЭИОС"
        }
      },
      {
        "num": 2,
        "time": "10:40 - 12:15",
        "subject": {
          "full_name": "Системный анализ",
          "kind": "Лекция",
          "auditoriums": "",
          "group": "Кориков А.М.",
          "note": "Реализуется в ЭИОС"
        }
      },
      {
        "num": 3,
        "time": "13:00 - 14:35",
        "subject": "Нет занятий"
      },
      {
        "num": 4,
        "time": "14:50 - 16:25",
        "subject": "Нет занятий"
      },
      {
        "num": 5,
        "time": "17:10 - 18:45",
        "subject": "Нет занятий"
      },
      {
        "num": 6,
        "time": "19:00 - 20:35",
        "subject": "Нет занятий"
      }
    ]
  }
}